main.py
pyniplay/__about__.py
pyniplay/__init__.py
pyniplay/cli.py
pyniplay/niplayThread.py
pyniplay/niplay_process.py
tests/testNiplayThreadKill.py
niplay-0.1.0.dist-info/METADATA
niplay-0.1.0.dist-info/WHEEL
niplay-0.1.0.dist-info/entry_points.txt
niplay-0.1.0.dist-info/top_level.txt
niplay-0.1.0.dist-info/RECORD
