Metadata-Version: 2.4
Name: niplay
Version: 0.1.0
Summary: Python warper for Niplay, a console app to play music
Author: Max
Project-URL: Homepage, https://github.com/xmaxrayx/pyniplay
Project-URL: Documentation, https://github.com/xmaxrayx/pyniplay
Project-URL: Source, https://github.com/xmaxrayx/pyniplay
Project-URL: Tracker, https://github.com/xmaxrayx/pyniplay/issues
Project-URL: Changelog, https://github.com/xmaxrayx/pyniplay/releases
Project-URL: AuthorGitGub, https://github.com/xmaxrayx/
Project-URL: AuthorLinktree, https://linktr.ee/xmaxrayx
Project-URL: AuthorPixiv, https://www.pixiv.net/en/users/76182182
